ado_pr_kit/__init__.py
ado_pr_kit/azdo_client.py
ado_pr_kit/config.py
ado_pr_kit/connect.py
ado_pr_kit/server.py
ado_pr_kit/server_sse.py
ado_pr_kit-0.2.8.dist-info/METADATA
ado_pr_kit-0.2.8.dist-info/WHEEL
ado_pr_kit-0.2.8.dist-info/entry_points.txt
ado_pr_kit-0.2.8.dist-info/licenses/LICENSE
ado_pr_kit-0.2.8.dist-info/RECORD
