Metadata-Version: 2.4
Name: ado-pr-kit
Version: 0.2.8
Summary: AdoPRKit: The complete toolbox for Azure DevOps Pull Requests (MCP)
Project-URL: Repository, https://github.com/om-surushe/AdoPRKit
Project-URL: Homepage, https://github.com/om-surushe/AdoPRKit
License-File: LICENSE
Requires-Python: >=3.10
Requires-Dist: black
Requires-Dist: build
Requires-Dist: fastapi
Requires-Dist: flake8
Requires-Dist: httpx
Requires-Dist: mcp
Requires-Dist: pre-commit
Requires-Dist: pydantic
Requires-Dist: pytest
Requires-Dist: pytest-mock
Requires-Dist: python-dotenv
Requires-Dist: requests
Requires-Dist: twine
Requires-Dist: typer
Requires-Dist: uvicorn
